nvidia/__init__.py
nvidia/nvtiff/__init__.py
nvidia/nvtiff/bin/__init__.py
nvidia/nvtiff/bin/nvtiff_0.dll
nvidia/nvtiff/include/__init__.py
nvidia/nvtiff/include/nvtiff.h
nvidia/nvtiff/include/nvtiff_version.h
nvidia_nvtiff_cu13-0.6.0.78.dist-info/licenses/LICENSE.txt
nvidia_nvtiff_cu13-0.6.0.78.dist-info/METADATA
nvidia_nvtiff_cu13-0.6.0.78.dist-info/WHEEL
nvidia_nvtiff_cu13-0.6.0.78.dist-info/top_level.txt
nvidia_nvtiff_cu13-0.6.0.78.dist-info/RECORD
